sure/__init__.py
sure/compat.py
sure/core.py
sure/deprecated.py
sure/magic.py
sure/old.py
sure/registry.py
sure/terminal.py
sure-1.4.9.dist-info/DESCRIPTION.rst
sure-1.4.9.dist-info/METADATA
sure-1.4.9.dist-info/RECORD
sure-1.4.9.dist-info/WHEEL
sure-1.4.9.dist-info/metadata.json
sure-1.4.9.dist-info/top_level.txt
